[
    {
        "title": "The Complete Guide to Setting Up Your First Home Server",
        "excerpt": "Learn how to build and configure a home server for file storage, media streaming, and personal cloud services.",
        "category": "Guide",
        "tag": "Guide",
        "readTime": "12 min",
        "timestamp": "2025-11-15T09:30:00",
        "image": "https://images.unsplash.com/photo-1599202860130-f600f4942194?w=200&h=200&fit=crop&crop=center",
        "url": "/articles/complete-guide-setting-up-first-home-server"
    },
    {
        "title": "Ultimate Guide to Choosing the Right Laptop for Programming",
        "excerpt": "Detailed comparison of specs, processors, RAM, and battery life for different programming needs and budgets.",
        "category": "Guide",
        "tag": "Guide",
        "readTime": "10 min",
        "timestamp": "2025-10-22T14:15:00",
        "image": "https://images.unsplash.com/photo-1518709268805-4e9042af2176?w=200&h=200&fit=crop&crop=center",
        "url": "/articles/ultimate-guide-choosing-right-laptop-programming"
    },
    {
        "title": "Python Web Scraping Tutorial for Beginners",
        "excerpt": "Learn web scraping using BeautifulSoup and Requests with practical examples and ethical considerations.",
        "category": "Tutorial",
        "tag": "Tutorial",
        "readTime": "8 min",
        "timestamp": "2025-12-03T11:45:00",
        "image": "https://images.unsplash.com/photo-1526374965328-7f61d4dc18c5?w=200&h=200&fit=crop&crop=center",
        "url": "/articles/python-web-scraping-tutorial-beginners"
    },
    {
        "title": "Building Your First React App: Step-by-Step Tutorial",
        "excerpt": "Create a weather app using React Hooks, API integration, and modern component architecture.",
        "category": "Tutorial",
        "tag": "Tutorial",
        "readTime": "15 min",
        "timestamp": "2025-09-18T16:20:00",
        "image": "https://images.unsplash.com/photo-1633356122544-f134324a6cee?w=200&h=200&fit=crop&crop=center",
        "url": "/articles/building-first-react-app-step-by-step-tutorial"
    },
    {
        "title": "10 Common Wi-Fi Problems and Their Solutions",
        "excerpt": "Fix slow connections, dropped signals, and authentication errors with these proven troubleshooting methods.",
        "category": "Solutions",
        "tag": "Solutions",
        "readTime": "6 min",
        "timestamp": "2025-08-27T10:10:00",
        "image": "https://images.unsplash.com/photo-1546054451-5d0ec4d4435c?w=200&h=200&fit=crop&crop=center",
        "url": "/articles/10-common-wifi-problems-and-their-solutions"
    },
    {
        "title": "Solving 'Disk Full' Errors on Windows and macOS",
        "excerpt": "Effective solutions to free up space and prevent storage-related system slowdowns on both operating systems.",
        "category": "Solutions",
        "tag": "Solutions",
        "readTime": "7 min",
        "timestamp": "2025-11-30T13:25:00",
        "image": "https://images.unsplash.com/photo-1558494949-ef010cbdcc31?w=200&h=200&fit=crop&crop=center",
        "url": "/articles/solving-disk-full-errors-windows-macos"
    },
    {
        "title": "AI in Healthcare: Current Applications and Future Potential",
        "excerpt": "Exploring how machine learning is transforming diagnosis, treatment, and patient care worldwide.",
        "category": "Insights",
        "tag": "Insights",
        "readTime": "9 min",
        "timestamp": "2025-10-05T15:40:00",
        "image": "https://images.unsplash.com/photo-1559757148-5c350d0d3c56?w=200&h=200&fit=crop&crop=center",
        "url": "/articles/ai-healthcare-current-applications-future-potential"
    },
    {
        "title": "The Metaverse Economy: How Virtual Reality is Creating Real Jobs",
        "excerpt": "Analysis of emerging career opportunities in VR development, virtual real estate, and digital fashion.",
        "category": "Insights",
        "tag": "Insights",
        "readTime": "11 min",
        "timestamp": "2025-12-12T12:05:00",
        "image": "https://images.unsplash.com/photo-1620641788421-7a1c342ea42e?w=200&h=200&fit=crop&crop=center",
        "url": "/articles/metaverse-economy-virtual-reality-creating-real-jobs"
    },
    {
        "title": "Learn Git and GitHub in 30 Days: A Structured Approach",
        "excerpt": "Master version control, branching strategies, and collaborative workflows through daily practice exercises.",
        "category": "Learn",
        "tag": "Learn",
        "readTime": "5 min",
        "timestamp": "2025-09-25T08:50:00",
        "image": "https://images.unsplash.com/photo-1633356122102-3fe601e05bd2?w=200&h=200&fit=crop&crop=center",
        "url": "/articles/learn-git-github-30-days-structured-approach"
    },
    {
        "title": "Understanding Blockchain Technology: From Basics to Smart Contracts",
        "excerpt": "Demystifying distributed ledgers, consensus mechanisms, and decentralized applications for beginners.",
        "category": "Learn",
        "tag": "Learn",
        "readTime": "14 min",
        "timestamp": "2025-11-08T17:35:00",
        "image": "https://images.unsplash.com/photo-1639762681485-074b7f938ba0?w=200&h=200&fit=crop&crop=center",
        "url": "/articles/understanding-blockchain-technology-basics-smart-contracts"
    },
    {
        "title": "Complete Walkthrough: Setting Up a Smart Home with Google Assistant",
        "excerpt": "Connect lights, thermostats, and security cameras for seamless voice-controlled home automation.",
        "category": "Walkthrough",
        "tag": "Walkthrough",
        "readTime": "13 min",
        "timestamp": "2025-10-17T14:55:00",
        "image": "https://images.unsplash.com/photo-1558618666-fcd25c85cd64?w=200&h=200&fit=crop&crop=center",
        "url": "/articles/complete-walkthrough-setting-up-smart-home-google-assistant"
    },
    {
        "title": "Ubuntu Server Installation Walkthrough for First-Time Users",
        "excerpt": "From downloading the ISO to configuring SSH and firewall settings - a complete visual guide.",
        "category": "Walkthrough",
        "tag": "Walkthrough",
        "readTime": "16 min",
        "timestamp": "2025-12-08T10:20:00",
        "image": "https://images.unsplash.com/photo-1618044619421-6e03fd6c5f5d?w=200&h=200&fit=crop&crop=center",
        "url": "/articles/ubuntu-server-installation-walkthrough-first-time-users"
    },
    {
        "title": "How to Build a Custom Mechanical Keyboard from Scratch",
        "excerpt": "Selecting switches, keycaps, and PCB components to create your perfect typing experience.",
        "category": "How-To",
        "tag": "How-To",
        "readTime": "8 min",
        "timestamp": "2025-09-12T16:45:00",
        "image": "https://images.unsplash.com/photo-1587829741301-dc798b83add3?w=200&h=200&fit=crop&crop=center",
        "url": "/articles/how-to-build-custom-mechanical-keyboard-from-scratch"
    },
    {
        "title": "How to Securely Wipe Your Hard Drive Before Selling Your Computer",
        "excerpt": "Step-by-step guide to completely erase data using industry-standard methods on Windows, macOS, and Linux.",
        "category": "How-To",
        "tag": "How-To",
        "readTime": "7 min",
        "timestamp": "2025-11-25T11:30:00",
        "image": "https://images.unsplash.com/photo-1581094794329-c8112a89af12?w=200&h=200&fit=crop&crop=center",
        "url": "/articles/how-to-securely-wipe-hard-drive-before-selling-computer"
    },
    {
        "title": "10 Excel Shortcuts That Will Save You Hours Every Week",
        "excerpt": "Master these keyboard combinations to dramatically increase your spreadsheet efficiency.",
        "category": "Tips & Tricks",
        "tag": "Tips & Tricks",
        "readTime": "5 min",
        "timestamp": "2025-10-08T09:15:00",
        "image": "https://images.unsplash.com/photo-1611926653458-09294b3142bf?w=200&h=200&fit=crop&crop=center",
        "url": "/articles/10-excel-shortcuts-save-hours-every-week"
    },
    {
        "title": "Chrome Developer Tools: Hidden Features You Should Know",
        "excerpt": "Advanced debugging techniques, performance monitoring, and CSS editing tricks for web developers.",
        "category": "Tips & Tricks",
        "tag": "Tips & Tricks",
        "readTime": "6 min",
        "timestamp": "2025-12-01T14:40:00",
        "image": "https://images.unsplash.com/photo-1563013544-824ae1b704d3?w=200&h=200&fit=crop&crop=center",
        "url": "/articles/chrome-developer-tools-hidden-features-you-should-know"
    },
    {
        "title": "MacBook Air M3 Review: Is It Still the Best Ultrabook?",
        "excerpt": "Testing performance, battery life, and display quality of Apple's latest thin-and-light laptop.",
        "category": "Tech Reviews",
        "tag": "Tech Reviews",
        "readTime": "9 min",
        "timestamp": "2025-11-05T13:20:00",
        "image": "https://images.unsplash.com/photo-1517336714731-489689fd1ca8?w=200&h=200&fit=crop&crop=center",
        "url": "/articles/macbook-air-m3-review-best-ultrabook"
    },
    {
        "title": "Samsung Galaxy S25 Ultra Review: Camera King Returns",
        "excerpt": "Evaluating the new 200MP camera, S-Pen functionality, and AI features in Samsung's latest flagship.",
        "category": "Tech Reviews",
        "tag": "Tech Reviews",
        "readTime": "11 min",
        "timestamp": "2025-12-10T10:55:00",
        "image": "https://images.unsplash.com/photo-1511707171634-5f897ff02aa9?w=200&h=200&fit=crop&crop=center",
        "url": "/articles/samsung-galaxy-s25-ultra-review-camera-king-returns"
    },
    {
        "title": "iPad Pro vs. Surface Pro 11: Which 2-in-1 is Right for You?",
        "excerpt": "Detailed comparison of performance, display quality, stylus experience, and ecosystem integration.",
        "category": "Comparisons",
        "tag": "Comparisons",
        "readTime": "12 min",
        "timestamp": "2025-09-28T15:25:00",
        "image": "https://images.unsplash.com/photo-1516035069371-29a1b244cc32?w=200&h=200&fit=crop&crop=center",
        "url": "/articles/ipad-pro-vs-surface-pro-11-which-2-in-1-right-for-you"
    },
    {
        "title": "Node.js vs Python: Which Backend Technology to Choose in 2026",
        "excerpt": "Comparing performance, scalability, learning curve, and job market demand for both technologies.",
        "category": "Comparisons",
        "tag": "Comparisons",
        "readTime": "10 min",
        "timestamp": "2025-10-30T12:10:00",
        "image": "https://images.unsplash.com/photo-1555066931-4365d14bab8c?w=200&h=200&fit=crop&crop=center",
        "url": "/articles/node-js-vs-python-which-backend-technology-choose-2026"
    },
    {
        "title": "Essential Linux Commands Every Developer Should Know",
        "excerpt": "Must-know terminal commands for file management, process monitoring, and system administration.",
        "category": "Essential",
        "tag": "Essential",
        "readTime": "8 min",
        "timestamp": "2025-11-18T08:45:00",
        "image": "https://images.unsplash.com/photo-1550745165-9bc0b252726f?w=200&h=200&fit=crop&crop=center",
        "url": "/articles/essential-linux-commands-every-developer-should-know"
    },
    {
        "title": "Essential Cybersecurity Tools for Small Businesses",
        "excerpt": "Affordable yet effective security solutions to protect your business from common online threats.",
        "category": "Essential",
        "tag": "Essential",
        "readTime": "7 min",
        "timestamp": "2025-12-05T16:30:00",
        "image": "https://images.unsplash.com/photo-1563986768609-322da13575f3?w=200&h=200&fit=crop&crop=center",
        "url": "/articles/essential-cybersecurity-tools-small-businesses"
    },
    {
        "title": "Comprehensive Guide to Cloud Computing: AWS, Azure, and GCP Compared",
        "excerpt": "In-depth analysis of pricing, services, and best use cases for the three major cloud providers.",
        "category": "Comprehensive",
        "tag": "Comprehensive",
        "readTime": "18 min",
        "timestamp": "2025-10-12T14:15:00",
        "image": "https://images.unsplash.com/photo-1542744173-8e7e53415bb0?w=200&h=200&fit=crop&crop=center",
        "url": "/articles/comprehensive-guide-cloud-computing-aws-azure-gcp-compared"
    },
    {
        "title": "Comprehensive Roadmap to Becoming a Full-Stack Developer in 2026",
        "excerpt": "Technologies, frameworks, and skills you need to master for both frontend and backend development.",
        "category": "Comprehensive",
        "tag": "Comprehensive",
        "readTime": "20 min",
        "timestamp": "2025-11-28T11:50:00",
        "image": "https://images.unsplash.com/photo-1522202176988-66273c2fd55f?w=200&h=200&fit=crop&crop=center",
        "url": "/articles/comprehensive-roadmap-becoming-full-stack-developer-2026"
    },
    {
        "title": "Boost Your Productivity with These 15 VS Code Extensions",
        "excerpt": "Curated list of extensions that will transform your coding workflow and save valuable time.",
        "category": "Productivity",
        "tag": "Productivity",
        "readTime": "6 min",
        "timestamp": "2025-09-15T10:25:00",
        "image": "https://images.unsplash.com/photo-1515879218367-8466d910aaa4?w=200&h=200&fit=crop&crop=center",
        "url": "/articles/boost-productivity-15-vs-code-extensions"
    },
    {
        "title": "Productivity Hacks for Remote Developers: Staying Focused and Efficient",
        "excerpt": "Time management techniques, tool recommendations, and workspace optimization for remote work.",
        "category": "Productivity",
        "tag": "Productivity",
        "readTime": "8 min",
        "timestamp": "2025-12-14T13:40:00",
        "image": "https://images.unsplash.com/photo-1580894894513-541e068a3e2b?w=200&h=200&fit=crop&crop=center",
        "url": "/articles/productivity-hacks-remote-developers-staying-focused-efficient"
    },
    {
        "title": "Git Branching Best Practices for Team Collaboration",
        "excerpt": "Implementing Git Flow, creating meaningful commits, and managing pull requests effectively.",
        "category": "Best Practices",
        "tag": "Best Practices",
        "readTime": "9 min",
        "timestamp": "2025-10-25T15:05:00",
        "image": "https://images.unsplash.com/photo-1551650975-87deedd944c3?w=200&h=200&fit=crop&crop=center",
        "url": "/articles/git-branching-best-practices-team-collaboration"
    },
    {
        "title": "API Design Best Practices: Building Scalable and Maintainable Interfaces",
        "excerpt": "RESTful principles, versioning strategies, error handling, and documentation standards.",
        "category": "Best Practices",
        "tag": "Best Practices",
        "readTime": "11 min",
        "timestamp": "2025-11-20T12:30:00",
        "image": "https://images.unsplash.com/photo-1558494949-ef010cbdcc31?w=200&h=200&fit=crop&crop=center",
        "url": "/articles/api-design-best-practices-building-scalable-maintainable-interfaces"
    },
    {
        "title": "Troubleshooting Common Docker Container Issues",
        "excerpt": "Solving network problems, volume mounting errors, and container startup failures in Docker environments.",
        "category": "Troubleshooting",
        "tag": "Troubleshooting",
        "readTime": "7 min",
        "timestamp": "2025-09-22T09:55:00",
        "image": "https://images.unsplash.com/photo-1627398242454-45a1465c2479?w=200&h=200&fit=crop&crop=center",
        "url": "/articles/troubleshooting-common-docker-container-issues"
    },
    {
        "title": "Troubleshooting Slow Internet: A Systematic Approach",
        "excerpt": "Diagnostic steps, tools, and solutions for identifying and fixing internet speed problems.",
        "category": "Troubleshooting",
        "tag": "Troubleshooting",
        "readTime": "6 min",
        "timestamp": "2025-12-07T14:20:00",
        "image": "https://images.unsplash.com/photo-1542744173-8e7e53415bb0?w=200&h=200&fit=crop&crop=center",
        "url": "/articles/troubleshooting-slow-internet-systematic-approach"
    },
    {
        "title": "Step-by-Step: Migrating Your Website from HTTP to HTTPS",
        "excerpt": "Complete guide to SSL certificate installation, configuration, and ensuring proper redirects.",
        "category": "Step-by-Step",
        "tag": "Step-by-Step",
        "readTime": "10 min",
        "timestamp": "2025-10-03T11:45:00",
        "image": "https://images.unsplash.com/photo-1551288049-bebda4e38f71?w=200&h=200&fit=crop&crop=center",
        "url": "/articles/step-by-step-migrating-website-http-to-https"
    },
    {
        "title": "Step-by-Step Guide to Setting Up a Raspberry Pi Media Center",
        "excerpt": "Installation, configuration, and optimization of Kodi or Plex on your Raspberry Pi 5.",
        "category": "Step-by-Step",
        "tag": "Step-by-Step",
        "readTime": "12 min",
        "timestamp": "2025-11-12T16:10:00",
        "image": "https://images.unsplash.com/photo-1581094794329-c8112a89af12?w=200&h=200&fit=crop&crop=center",
        "url": "/articles/step-by-step-guide-setting-up-raspberry-pi-media-center"
    },
    {
        "title": "Top 10 Productivity Tools for Software Developers in 2026",
        "excerpt": "AI-powered code assistants, project management platforms, and automation tools that save time.",
        "category": "Productivity Tools",
        "tag": "Productivity Tools",
        "readTime": "8 min",
        "timestamp": "2025-09-30T13:35:00",
        "image": "https://images.unsplash.com/photo-1581091226033-d5c48150dbaa?w=200&h=200&fit=crop&crop=center",
        "url": "/articles/top-10-productivity-tools-software-developers-2026"
    },
    {
        "title": "Notion vs Obsidian: Which Knowledge Management Tool is Better?",
        "excerpt": "Comparing features, customization, and workflow integration for personal knowledge bases.",
        "category": "Productivity Tools",
        "tag": "Productivity Tools",
        "readTime": "9 min",
        "timestamp": "2025-12-02T10:00:00",
        "image": "https://images.unsplash.com/photo-1611224923853-80b023f02d71?w=200&h=200&fit=crop&crop=center",
        "url": "/articles/notion-vs-obsidian-which-knowledge-management-tool-better"
    },
    {
        "title": "DIY Smart Mirror: Build Your Own with Raspberry Pi",
        "excerpt": "Create a voice-controlled smart mirror that displays weather, calendar, and news updates.",
        "category": "Tech DIY",
        "tag": "Tech DIY",
        "readTime": "15 min",
        "timestamp": "2026-02-08T22:09:00",
        "image": "https://images.unsplash.com/photo-1581094794329-c8112a89af12?w=200&h=200&fit=crop&crop=center",
        "url": "/articles/diy-smart-mirror-build-your-own-raspberry-pi"
    },
      {
        "title": "DIY Smaart Mirror: Build Your Own with Raspberry Pi",
        "excerpt": "Create a voice-controlled smart mirror that displays weather, calendar, and news updates.",
        "category": "Tech DIY",
        "tag": "Tech DIY",
        "readTime": "15 min",
        "timestamp": "2026-02-08T22:09:00",
        "image": "https://images.unsplash.com/photo-1581094794329-c8112a89af12?w=200&h=200&fit=crop&crop=center",
        "url": "/articles/diy-smart-mirror-build-your-own-raspberry-pi"
    },
    {
        "title": "Building a Custom Game Controller with Arduino",
        "excerpt": "From soldering components to programming button mapping for retro gaming systems.",
        "category": "Tech DIY",
        "tag": "Tech DIY",
        "readTime": "14 min",
        "timestamp": "2026-02-07T12:25:00",
        "image": "https://images.unsplash.com/photo-1581091226033-d5c48150dbaa?w=200&h=200&fit=crop&crop=center",
        "url": "/articles/building-custom-game-controller-arduino"
    },
    {
        "title": "7 Critical Security Tips for Working from Public Wi-Fi",
        "excerpt": "Protect your data and privacy when using coffee shop, airport, or hotel internet connections.",
        "category": "Security Tips",
        "tag": "Security Tips",
        "readTime": "5 min",
        "timestamp": "2025-09-10T08:40:00",
        "image": "https://images.unsplash.com/photo-1550751827-4bd374c3f58b?w=200&h=200&fit=crop&crop=center",
        "url": "/articles/7-critical-security-tips-working-public-wifi"
    },
    {
        "title": "Password Management Best Practices: Beyond Just Using a Manager",
        "excerpt": "Creating strong passwords, enabling 2FA, and avoiding common authentication pitfalls.",
        "category": "Security Tips",
        "tag": "Security Tips",
        "readTime": "6 min",
        "timestamp": "2019-12-16T15:15:00",
        "image": "https://images.unsplash.com/photo-1563986768609-322da13575f3?w=200&h=200&fit=crop&crop=center",
        "url": "/articles/password-management-best-practices-beyond-just-using-manager"
    },
    {
        "title": "Debunked: The 'Download More RAM' Myth and How Memory Actually Works",
        "excerpt": "Understanding physical vs virtual memory, and why you can't actually download additional RAM.",
        "category": "Tech Myth",
        "tag": "Tech Myth",
        "readTime": "7 min",
        "timestamp": "2026-02-14T11:20:00",
        "image": "https://images.unsplash.com/photo-1517336714731-489689fd1ca8?w=200&h=200&fit=crop&crop=center",
        "url": "/articles/debunked-download-more-ram-myth-how-memory-actually-works"
    },
    {
        "title": "Truth About Macs and Viruses: Are They Really Immune?",
        "excerpt": "Examining the myth of Mac invulnerability and understanding real security risks for Apple users.",
        "category": "Tech Myth",
        "tag": "Tech Myth",
        "readTime": "8 min",
        "timestamp": "2025-11-10T13:55:00",
        "image": "https://images.unsplash.com/photo-1516035069371-29a1b244cc32?w=200&h=200&fit=crop&crop=center",
        "url": "/articles/truth-about-macs-viruses-are-they-really-immune"
    }
]
